ClockworkOrange/ClockworkOrange.py
ClockworkOrange/__init__.py
ClockworkOrange-0.0.1.dist-info/DESCRIPTION.rst
ClockworkOrange-0.0.1.dist-info/METADATA
ClockworkOrange-0.0.1.dist-info/RECORD
ClockworkOrange-0.0.1.dist-info/WHEEL
ClockworkOrange-0.0.1.dist-info/metadata.json
ClockworkOrange-0.0.1.dist-info/top_level.txt
